networkcommons/__init__.py
networkcommons/_conf.py
networkcommons/_imports.py
networkcommons/_metadata.py
networkcommons/_session.py
networkcommons/data/__init__.py
networkcommons/data/_builtin.py
networkcommons/data/config.yaml
networkcommons/data/datasets.yaml
networkcommons/data/network/__init__.py
networkcommons/data/network/_liana.py
networkcommons/data/network/_moon.py
networkcommons/data/network/_omnipath.py
networkcommons/data/omics/__init__.py
networkcommons/data/omics/_common.py
networkcommons/data/omics/_cptac.py
networkcommons/data/omics/_decryptm.py
networkcommons/data/omics/_deseq2.py
networkcommons/data/omics/_nci60.py
networkcommons/data/omics/_panacea.py
networkcommons/data/omics/_scperturb.py
networkcommons/data/urls.yaml
networkcommons/eval/__init__.py
networkcommons/eval/_metrics.py
networkcommons/methods/__init__.py
networkcommons/methods/_causal.py
networkcommons/methods/_graph.py
networkcommons/methods/_moon.py
networkcommons/network/__init__.py
networkcommons/network/_bootstrap/__init__.py
networkcommons/network/_bootstrap/_base.py
networkcommons/network/_bootstrap/_copy.py
networkcommons/network/_bootstrap/_df.py
networkcommons/network/_bootstrap/_edgelist.py
networkcommons/network/_constants.py
networkcommons/network/_formats/__init__.py
networkcommons/network/_formats/_igraph.py
networkcommons/network/_formats/_networkx.py
networkcommons/network/_network.py
networkcommons/noi/__init__.py
networkcommons/noi/_node.py
networkcommons/noi/_noi.py
networkcommons/utils.py
networkcommons/visual/__init__.py
networkcommons/visual/_aux.py
networkcommons/visual/_network_stats.py
networkcommons/visual/_rnaseq.py
networkcommons/visual/_styles.py
networkcommons/visual/_vis_networkx.py
networkcommons/visual/_vis_yfiles.py
networkcommons/visual/_yfiles_styles.py
networkcommons-0.4.3.dist-info/LICENSE
networkcommons-0.4.3.dist-info/METADATA
networkcommons-0.4.3.dist-info/WHEEL
networkcommons-0.4.3.dist-info/RECORD
